sentience/__init__.py
sentience/history.py
sentience/signature_utils.py
sentience-0.0.2.dist-info/METADATA
sentience-0.0.2.dist-info/WHEEL
sentience-0.0.2.dist-info/RECORD
