Metadata-Version: 2.1
Name: sentience
Version: 0.0.2
Summary: 
Author: Kaspar Peterson
Author-email: kaspar@galadriel.com
Requires-Python: >=3.10,<4.0
Classifier: Programming Language :: Python :: 3
Classifier: Programming Language :: Python :: 3.10
Classifier: Programming Language :: Python :: 3.11
Classifier: Programming Language :: Python :: 3.12
Classifier: Programming Language :: Python :: 3.13
Provides-Extra: dev
Requires-Dist: black (>=24.8.0,<25.0.0) ; extra == "dev"
Requires-Dist: build (>=1.2.2,<2.0.0) ; extra == "dev"
Requires-Dist: openai (>=1.55.3,<2.0.0)
Requires-Dist: pynacl (>=1.5.0,<2.0.0)
Requires-Dist: pytest (>=8.3.2,<9.0.0) ; extra == "dev"
Requires-Dist: pytest-asyncio (==0.24.0) ; extra == "dev"
Requires-Dist: pytest-mock (>=3.14.0,<4.0.0) ; extra == "dev"
Requires-Dist: requests (==2.31.0)
Requires-Dist: twine (>=5.1.1,<6.0.0) ; extra == "dev"
